algoliaqb/__init__.py
algoliaqb-0.1.dist-info/LICENSE
algoliaqb-0.1.dist-info/METADATA
algoliaqb-0.1.dist-info/WHEEL
algoliaqb-0.1.dist-info/top_level.txt
algoliaqb-0.1.dist-info/RECORD
