Metadata-Version: 2.1
Name: algoliaqb
Version: 0.1
Summary: Algolia Query Builder
Home-page: http://github.com/ryanb58/algoliaqb
Author: Taylor Brazelton
Author-email: taylor.r.brazelton@gmail.com
License: MIT
Platform: UNKNOWN
